djangochannelsrestframework/__init__.py
djangochannelsrestframework/consumers.py
djangochannelsrestframework/decorators.py
djangochannelsrestframework/generics.py
djangochannelsrestframework/mixins.py
djangochannelsrestframework/pagination.py
djangochannelsrestframework/permissions.py
djangochannelsrestframework/scope_utils.py
djangochannelsrestframework/settings.py
djangochannelsrestframework/observer/__init__.py
djangochannelsrestframework/observer/base_observer.py
djangochannelsrestframework/observer/generics.py
djangochannelsrestframework/observer/model_observer.py
djangochannelsrestframework/observer/observer.py
djangochannelsrestframework/observer/utils.py
djangochannelsrestframework-1.2.0.dist-info/LICENSE
djangochannelsrestframework-1.2.0.dist-info/METADATA
djangochannelsrestframework-1.2.0.dist-info/WHEEL
djangochannelsrestframework-1.2.0.dist-info/top_level.txt
djangochannelsrestframework-1.2.0.dist-info/RECORD
