Metadata-Version: 2.1
Name: djangochannelsrestframework
Version: 1.2.0
Summary: RESTful API for WebSockets using django channels.
Home-page: https://github.com/NilCoalescing/djangochannelsrestframework
Author: LostMoa Limited
Author-email: info@nilcoalescing.com
License: MIT
Classifier: Development Status :: 5 - Production/Stable
Classifier: Environment :: Web Environment
Classifier: Intended Audience :: Developers
Classifier: Operating System :: OS Independent
Classifier: License :: OSI Approved :: MIT License
Classifier: Programming Language :: Python :: 3.8
Classifier: Programming Language :: Python :: 3.9
Classifier: Programming Language :: Python :: 3.10
Classifier: Programming Language :: Python :: 3.11
Classifier: Framework :: Django
Classifier: Topic :: Internet :: WWW/HTTP
Requires-Python: >=3.8
Provides-Extra: tests
License-File: LICENSE
